ndbviewer/__init__.py
ndbviewer/ndbviewer.py
ndbviewer-0.0.3.dist-info/LICENSE
ndbviewer-0.0.3.dist-info/METADATA
ndbviewer-0.0.3.dist-info/WHEEL
ndbviewer-0.0.3.dist-info/top_level.txt
ndbviewer-0.0.3.dist-info/RECORD
