Metadata-Version: 2.1
Name: ndbviewer
Version: 0.0.3
Summary: This module allows you to view local data from your Google Cloud NDB projects using thee Google Datastore Emulator.
Home-page: https://github.com/ReddingSoftware/Google_NDB_Emulator
Author: Brandon Wegner
Author-email: brandon.wegner@reddingsoftware.com
License: UNKNOWN
Project-URL: Bug Tracker, https://github.com/ReddingSoftware/Google_NDB_Emulator/issues
Platform: UNKNOWN
Classifier: Programming Language :: Python :: 3
Classifier: License :: OSI Approved :: MIT License
Classifier: Operating System :: OS Independent
Requires-Python: >=3.6
License-File: LICENSE
